pbshm/autostat/__init__.py
pbshm/autostat/autostat.py
pbshm/autostat/templates/list-populations.html
pbshm/autostat/templates/statistics.html
pbshm/cleanse/__init__.py
pbshm/cleanse/commands.py
pbshm/cleanse/models.py
pbshm/cleanse/procedures.py
pbshm/cleanse/routes.py
pbshm/cleanse/templates/details.html
pbshm_channel_toolbox-0.1.4.dist-info/licenses/LICENSE
pbshm_channel_toolbox-0.1.4.dist-info/METADATA
pbshm_channel_toolbox-0.1.4.dist-info/WHEEL
pbshm_channel_toolbox-0.1.4.dist-info/top_level.txt
pbshm_channel_toolbox-0.1.4.dist-info/RECORD
