Metadata-Version: 2.4
Name: pbshm-channel-toolbox
Version: 0.1.4
Summary: PBSHM Channel Toolbox
Author-email: Dan Brennan <d.s.brennan@sheffield.ac.uk>
License:                     GNU AFFERO GENERAL PUBLIC LICENSE
Project-URL: homepage, https://github.com/dsbrennan/channel-tools
Classifier: License :: OSI Approved :: GNU Affero General Public License v3 or later (AGPLv3+)
Classifier: Programming Language :: Python :: 3
Classifier: Framework :: Flask
Requires-Python: >=3.9.18
License-File: LICENSE
Requires-Dist: pbshm-core==1.1.6
Requires-Dist: bokeh==3.7.3
Dynamic: license-file
